[{"title": "Financial News Article 1 for 2025-04-21", "source": "Historical News Scraper", "published_at": "2025-04-21T22:53:00Z", "content": "This is simulated content for article 1 on 2025-04-21", "url": "https://example.com/news/2025-04-21/1"}, {"title": "Financial News Article 2 for 2025-04-21", "source": "Historical News Scraper", "published_at": "2025-04-21T03:30:00Z", "content": "This is simulated content for article 2 on 2025-04-21", "url": "https://example.com/news/2025-04-21/2"}, {"title": "Financial News Article 3 for 2025-04-21", "source": "Historical News Scraper", "published_at": "2025-04-21T12:42:00Z", "content": "This is simulated content for article 3 on 2025-04-21", "url": "https://example.com/news/2025-04-21/3"}, {"title": "Financial News Article 4 for 2025-04-21", "source": "Historical News Scraper", "published_at": "2025-04-21T22:52:00Z", "content": "This is simulated content for article 4 on 2025-04-21", "url": "https://example.com/news/2025-04-21/4"}, {"title": "Financial News Article 5 for 2025-04-21", "source": "Historical News Scraper", "published_at": "2025-04-21T18:25:00Z", "content": "This is simulated content for article 5 on 2025-04-21", "url": "https://example.com/news/2025-04-21/5"}, {"title": "Financial News Article 6 for 2025-04-21", "source": "Historical News Scraper", "published_at": "2025-04-21T16:02:00Z", "content": "This is simulated content for article 6 on 2025-04-21", "url": "https://example.com/news/2025-04-21/6"}, {"title": "Financial News Article 7 for 2025-04-21", "source": "Historical News Scraper", "published_at": "2025-04-21T09:25:00Z", "content": "This is simulated content for article 7 on 2025-04-21", "url": "https://example.com/news/2025-04-21/7"}, {"title": "Financial News Article 8 for 2025-04-21", "source": "Historical News Scraper", "published_at": "2025-04-21T19:17:00Z", "content": "This is simulated content for article 8 on 2025-04-21", "url": "https://example.com/news/2025-04-21/8"}, {"title": "Financial News Article 9 for 2025-04-21", "source": "Historical News Scraper", "published_at": "2025-04-21T02:53:00Z", "content": "This is simulated content for article 9 on 2025-04-21", "url": "https://example.com/news/2025-04-21/9"}]