[{"title": "[r/wallstreetbets] Financial Discussion Post 1 for 2023-11-18", "subreddit": "wallstreetbets", "created_utc": "2023-11-18T19:20:00Z", "selftext": "This is simulated content for Reddit post 1 on 2023-11-18 in r/wallstreetbets", "permalink": "/r/wallstreetbets/comments/2023-11-180", "score": 127, "num_comments": 127}, {"title": "[r/wallstreetbets] Financial Discussion Post 2 for 2023-11-18", "subreddit": "wallstreetbets", "created_utc": "2023-11-18T00:09:00Z", "selftext": "This is simulated content for Reddit post 2 on 2023-11-18 in r/wallstreetbets", "permalink": "/r/wallstreetbets/comments/2023-11-181", "score": 270, "num_comments": 141}, {"title": "[r/wallstreetbets] Financial Discussion Post 3 for 2023-11-18", "subreddit": "wallstreetbets", "created_utc": "2023-11-18T20:26:00Z", "selftext": "This is simulated content for Reddit post 3 on 2023-11-18 in r/wallstreetbets", "permalink": "/r/wallstreetbets/comments/2023-11-182", "score": 146, "num_comments": 146}, {"title": "[r/wallstreetbets] Financial Discussion Post 4 for 2023-11-18", "subreddit": "wallstreetbets", "created_utc": "2023-11-18T00:46:00Z", "selftext": "This is simulated content for Reddit post 4 on 2023-11-18 in r/wallstreetbets", "permalink": "/r/wallstreetbets/comments/2023-11-183", "score": 187, "num_comments": 144}, {"title": "[r/wallstreetbets] Financial Discussion Post 5 for 2023-11-18", "subreddit": "wallstreetbets", "created_utc": "2023-11-18T01:48:00Z", "selftext": "This is simulated content for Reddit post 5 on 2023-11-18 in r/wallstreetbets", "permalink": "/r/wallstreetbets/comments/2023-11-184", "score": 970, "num_comments": 5}, {"title": "[r/wallstreetbets] Financial Discussion Post 6 for 2023-11-18", "subreddit": "wallstreetbets", "created_utc": "2023-11-18T02:33:00Z", "selftext": "This is simulated content for Reddit post 6 on 2023-11-18 in r/wallstreetbets", "permalink": "/r/wallstreetbets/comments/2023-11-185", "score": 943, "num_comments": 74}, {"title": "[r/investing] Financial Discussion Post 1 for 2023-11-18", "subreddit": "investing", "created_utc": "2023-11-18T14:23:00Z", "selftext": "This is simulated content for Reddit post 1 on 2023-11-18 in r/investing", "permalink": "/r/investing/comments/2023-11-180", "score": 298, "num_comments": 118}, {"title": "[r/investing] Financial Discussion Post 2 for 2023-11-18", "subreddit": "investing", "created_utc": "2023-11-18T16:45:00Z", "selftext": "This is simulated content for Reddit post 2 on 2023-11-18 in r/investing", "permalink": "/r/investing/comments/2023-11-181", "score": 952, "num_comments": 111}, {"title": "[r/investing] Financial Discussion Post 3 for 2023-11-18", "subreddit": "investing", "created_utc": "2023-11-18T07:29:00Z", "selftext": "This is simulated content for Reddit post 3 on 2023-11-18 in r/investing", "permalink": "/r/investing/comments/2023-11-182", "score": 201, "num_comments": 38}, {"title": "[r/investing] Financial Discussion Post 4 for 2023-11-18", "subreddit": "investing", "created_utc": "2023-11-18T12:55:00Z", "selftext": "This is simulated content for Reddit post 4 on 2023-11-18 in r/investing", "permalink": "/r/investing/comments/2023-11-183", "score": 893, "num_comments": 89}, {"title": "[r/investing] Financial Discussion Post 5 for 2023-11-18", "subreddit": "investing", "created_utc": "2023-11-18T19:22:00Z", "selftext": "This is simulated content for Reddit post 5 on 2023-11-18 in r/investing", "permalink": "/r/investing/comments/2023-11-184", "score": 8, "num_comments": 77}, {"title": "[r/investing] Financial Discussion Post 6 for 2023-11-18", "subreddit": "investing", "created_utc": "2023-11-18T01:34:00Z", "selftext": "This is simulated content for Reddit post 6 on 2023-11-18 in r/investing", "permalink": "/r/investing/comments/2023-11-185", "score": 826, "num_comments": 197}, {"title": "[r/stocks] Financial Discussion Post 1 for 2023-11-18", "subreddit": "stocks", "created_utc": "2023-11-18T00:45:00Z", "selftext": "This is simulated content for Reddit post 1 on 2023-11-18 in r/stocks", "permalink": "/r/stocks/comments/2023-11-180", "score": 702, "num_comments": 105}, {"title": "[r/stocks] Financial Discussion Post 2 for 2023-11-18", "subreddit": "stocks", "created_utc": "2023-11-18T08:42:00Z", "selftext": "This is simulated content for Reddit post 2 on 2023-11-18 in r/stocks", "permalink": "/r/stocks/comments/2023-11-181", "score": 106, "num_comments": 112}, {"title": "[r/stocks] Financial Discussion Post 3 for 2023-11-18", "subreddit": "stocks", "created_utc": "2023-11-18T23:55:00Z", "selftext": "This is simulated content for Reddit post 3 on 2023-11-18 in r/stocks", "permalink": "/r/stocks/comments/2023-11-182", "score": 206, "num_comments": 93}, {"title": "[r/stocks] Financial Discussion Post 4 for 2023-11-18", "subreddit": "stocks", "created_utc": "2023-11-18T21:23:00Z", "selftext": "This is simulated content for Reddit post 4 on 2023-11-18 in r/stocks", "permalink": "/r/stocks/comments/2023-11-183", "score": 537, "num_comments": 184}]